vdata/IO/__init__.py
vdata/IO/errors.py
vdata/IO/logger.py
vdata/__init__.py
vdata/_meta.py
vdata/_typing.py
vdata/anndata_proxy/__init__.py
vdata/anndata_proxy/anndata.py
vdata/anndata_proxy/containers.py
vdata/anndata_proxy/dataframe.py
vdata/array_view.py
vdata/cli.py
vdata/data/__init__.py
vdata/data/_indexing.py
vdata/data/_parse/__init__.py
vdata/data/_parse/anndata.py
vdata/data/_parse/data.py
vdata/data/_parse/objects/__init__.py
vdata/data/_parse/objects/layers.py
vdata/data/_parse/objects/objects.py
vdata/data/_parse/objects/obs.py
vdata/data/_parse/objects/uns.py
vdata/data/_parse/objects/var.py
vdata/data/_parse/time.py
vdata/data/_parse/utils.py
vdata/data/arrays/__init__.py
vdata/data/arrays/base.py
vdata/data/arrays/layers.py
vdata/data/arrays/lazy.py
vdata/data/arrays/obs.py
vdata/data/arrays/var.py
vdata/data/arrays/view.py
vdata/data/concatenate.py
vdata/data/convert.py
vdata/data/hash.py
vdata/data/name.py
vdata/data/read.py
vdata/data/vdata.py
vdata/data/view.py
vdata/data/write.py
vdata/names.py
vdata/py.typed
vdata/tdf/__init__.py
vdata/tdf/_parse.py
vdata/tdf/base.py
vdata/tdf/dataframe.py
vdata/tdf/index.py
vdata/tdf/indexers.py
vdata/tdf/indexing.py
vdata/tdf/view.py
vdata/timepoint/__init__.py
vdata/timepoint/_functions.py
vdata/timepoint/_typing.py
vdata/timepoint/array.py
vdata/timepoint/index.py
vdata/timepoint/range.py
vdata/timepoint/timepoint.py
vdata/update/__init__.py
vdata/update/array.py
vdata/update/dict.py
vdata/update/tdf.py
vdata/update/update.py
vdata/update/utils.py
vdata/update/vdf.py
vdata/utils.py
vdata-0.3.6.dist-info/licenses/LICENSE
vdata-0.3.6.dist-info/WHEEL
vdata-0.3.6.dist-info/entry_points.txt
vdata-0.3.6.dist-info/METADATA
vdata-0.3.6.dist-info/RECORD
