Metadata-Version: 2.4
Name: vdata
Version: 0.3.6
Summary: Annotated multivariate observation of timestamped data
Author: Matteo Bouvier
Author-email: Matteo Bouvier <matteo.bouvier@hotmail.fr>
License-Expression: CECILL-B
License-File: LICENSE
Requires-Dist: tqdm>=4.66.1
Requires-Dist: anndata>=0.10.4
Requires-Dist: scipy>=1.12.0
Requires-Dist: numpy-indexed>=0.3.7
Requires-Dist: ch5mpy>=0.5.1
Requires-Dist: ezarr>=1.1.4
Requires-Dist: h5dataframe>=0.2.3 ; extra == 'update'
Requires-Python: >=3.12
Provides-Extra: update
